__init__.py
insideopt_sort.py
sort.py
insideopt_sort-0.1.dist-info/METADATA
insideopt_sort-0.1.dist-info/WHEEL
insideopt_sort-0.1.dist-info/top_level.txt
insideopt_sort-0.1.dist-info/RECORD
