Metadata-Version: 2.1
Name: insideopt-sort
Version: 0.1
Summary: A module that sorts numbers
Author: Meinolf Sellmann
Author-email: meinolf@gmail.com
